odoo/addons/hr_contract_default_trial_length/README.rst
odoo/addons/hr_contract_default_trial_length/__init__.py
odoo/addons/hr_contract_default_trial_length/__manifest__.py
odoo/addons/hr_contract_default_trial_length/i18n/ar.po
odoo/addons/hr_contract_default_trial_length/i18n/cs_CZ.po
odoo/addons/hr_contract_default_trial_length/i18n/de.po
odoo/addons/hr_contract_default_trial_length/i18n/es.po
odoo/addons/hr_contract_default_trial_length/i18n/fi.po
odoo/addons/hr_contract_default_trial_length/i18n/fr.po
odoo/addons/hr_contract_default_trial_length/i18n/hi_IN.po
odoo/addons/hr_contract_default_trial_length/i18n/hr.po
odoo/addons/hr_contract_default_trial_length/i18n/hr_contract_default_trial_length.pot
odoo/addons/hr_contract_default_trial_length/i18n/it.po
odoo/addons/hr_contract_default_trial_length/i18n/lt.po
odoo/addons/hr_contract_default_trial_length/i18n/nl_NL.po
odoo/addons/hr_contract_default_trial_length/i18n/pt_BR.po
odoo/addons/hr_contract_default_trial_length/i18n/ro.po
odoo/addons/hr_contract_default_trial_length/i18n/sl.po
odoo/addons/hr_contract_default_trial_length/models/__init__.py
odoo/addons/hr_contract_default_trial_length/models/hr_contract.py
odoo/addons/hr_contract_default_trial_length/models/hr_contract_type.py
odoo/addons/hr_contract_default_trial_length/readme/CONFIGURE.rst
odoo/addons/hr_contract_default_trial_length/readme/CONTRIBUTORS.rst
odoo/addons/hr_contract_default_trial_length/readme/DESCRIPTION.rst
odoo/addons/hr_contract_default_trial_length/readme/INSTALL.rst
odoo/addons/hr_contract_default_trial_length/readme/ROADMAP.rst
odoo/addons/hr_contract_default_trial_length/readme/USAGE.rst
odoo/addons/hr_contract_default_trial_length/static/description/icon.png
odoo/addons/hr_contract_default_trial_length/static/description/index.html
odoo/addons/hr_contract_default_trial_length/tests/__init__.py
odoo/addons/hr_contract_default_trial_length/tests/test_trial_length.py
odoo11_addon_hr_contract_default_trial_length-11.0.1.0.0.99.dev7.dist-info/METADATA
odoo11_addon_hr_contract_default_trial_length-11.0.1.0.0.99.dev7.dist-info/WHEEL
odoo11_addon_hr_contract_default_trial_length-11.0.1.0.0.99.dev7.dist-info/top_level.txt
odoo11_addon_hr_contract_default_trial_length-11.0.1.0.0.99.dev7.dist-info/RECORD
